{
    "easycom": {
    	"^z-(.*)": "@zebra-ui/swiper/components/z-$1/z-$1.vue"
    },
	"pages": [{
		"path": "pages/login/login",
		"style": {
			"navigationBarBackgroundColor": "#A3A9E4",
			"navigationBarTextStyle": "black",
			"navigationBarTitleText": "登录"
		}
	}, {
		"path": "pages/register/register",
		"style": {
			"navigationBarBackgroundColor": "#A3A9E4",
			"navigationBarTextStyle": "black",
			"navigationBarTitleText": "注册"
		}
	}, {
		"path": "pages/forget/forget",
		"style": {
			"navigationBarBackgroundColor": "#A3A9E4",
			"navigationBarTextStyle": "black",
			"navigationBarTitleText": "忘记密码"
		}
	}, {
		"path": "pages/center/center",
		"style": {
			"navigationBarBackgroundColor": "#A3A9E4",
			"navigationBarTextStyle": "black",
			"navigationBarTitleText": "我的"
		}
	}, {
		"path": "pages/user-info/user-info",
		"style": {
			"navigationBarBackgroundColor": "#A3A9E4",
			"navigationBarTextStyle": "black",
			"navigationBarTitleText": "用户信息"
		}
	}
	, {
		"path": "pages/news-detail/news-detail",
		"style": {
			"navigationBarBackgroundColor": "#A3A9E4",
			"navigationBarTextStyle": "black",
			"navigationBarTitleText": "资讯详情"
		}
	}
	,{
		"path": "pages/yonghu/list",
		"style": {
			"navigationBarBackgroundColor": "#A3A9E4",
			"navigationBarTextStyle": "black"
		}
	},{
		"path": "pages/yonghu/add-or-update",
		"style": {
			"navigationBarBackgroundColor": "#A3A9E4",
			"navigationBarTextStyle": "black"
		}
	},{
		"path": "pages/yonghu/detail",
		"style": {
			"navigationBarBackgroundColor": "#A3A9E4",
			"navigationBarTextStyle": "black"
		}
	}
	,{
		"path": "pages/faqiren/list",
		"style": {
			"navigationBarBackgroundColor": "#A3A9E4",
			"navigationBarTextStyle": "black"
		}
	},{
		"path": "pages/faqiren/add-or-update",
		"style": {
			"navigationBarBackgroundColor": "#A3A9E4",
			"navigationBarTextStyle": "black"
		}
	},{
		"path": "pages/faqiren/detail",
		"style": {
			"navigationBarBackgroundColor": "#A3A9E4",
			"navigationBarTextStyle": "black"
		}
	}
	,{
		"path": "pages/jingdianxinxi/list",
		"style": {
			"navigationBarBackgroundColor": "#A3A9E4",
			"navigationBarTextStyle": "black"
		}
	},{
		"path": "pages/jingdianxinxi/add-or-update",
		"style": {
			"navigationBarBackgroundColor": "#A3A9E4",
			"navigationBarTextStyle": "black"
		}
	},{
		"path": "pages/jingdianxinxi/detail",
		"style": {
			"navigationBarBackgroundColor": "#A3A9E4",
			"navigationBarTextStyle": "black"
		}
	}
	,{
		"path": "pages/jingdianfenlei/list",
		"style": {
			"navigationBarBackgroundColor": "#A3A9E4",
			"navigationBarTextStyle": "black"
		}
	},{
		"path": "pages/jingdianfenlei/add-or-update",
		"style": {
			"navigationBarBackgroundColor": "#A3A9E4",
			"navigationBarTextStyle": "black"
		}
	},{
		"path": "pages/jingdianfenlei/detail",
		"style": {
			"navigationBarBackgroundColor": "#A3A9E4",
			"navigationBarTextStyle": "black"
		}
	}
	,{
		"path": "pages/pintuanlvyou/list",
		"style": {
			"navigationBarBackgroundColor": "#A3A9E4",
			"navigationBarTextStyle": "black"
		}
	},{
		"path": "pages/pintuanlvyou/add-or-update",
		"style": {
			"navigationBarBackgroundColor": "#A3A9E4",
			"navigationBarTextStyle": "black"
		}
	},{
		"path": "pages/pintuanlvyou/detail",
		"style": {
			"navigationBarBackgroundColor": "#A3A9E4",
			"navigationBarTextStyle": "black"
		}
	}
	,{
		"path": "pages/cantuanxinxi/list",
		"style": {
			"navigationBarBackgroundColor": "#A3A9E4",
			"navigationBarTextStyle": "black"
		}
	},{
		"path": "pages/cantuanxinxi/add-or-update",
		"style": {
			"navigationBarBackgroundColor": "#A3A9E4",
			"navigationBarTextStyle": "black"
		}
	},{
		"path": "pages/cantuanxinxi/detail",
		"style": {
			"navigationBarBackgroundColor": "#A3A9E4",
			"navigationBarTextStyle": "black"
		}
	}
	,{
		"path": "pages/pintuandingdan/list",
		"style": {
			"navigationBarBackgroundColor": "#A3A9E4",
			"navigationBarTextStyle": "black"
		}
	},{
		"path": "pages/pintuandingdan/add-or-update",
		"style": {
			"navigationBarBackgroundColor": "#A3A9E4",
			"navigationBarTextStyle": "black"
		}
	},{
		"path": "pages/pintuandingdan/detail",
		"style": {
			"navigationBarBackgroundColor": "#A3A9E4",
			"navigationBarTextStyle": "black"
		}
	}
	,{
		"path": "pages/pingjiaxinxi/list",
		"style": {
			"navigationBarBackgroundColor": "#A3A9E4",
			"navigationBarTextStyle": "black"
		}
	},{
		"path": "pages/pingjiaxinxi/add-or-update",
		"style": {
			"navigationBarBackgroundColor": "#A3A9E4",
			"navigationBarTextStyle": "black"
		}
	},{
		"path": "pages/pingjiaxinxi/detail",
		"style": {
			"navigationBarBackgroundColor": "#A3A9E4",
			"navigationBarTextStyle": "black"
		}
	}
	,{
		"path": "pages/storeup/list",
		"style": {
			"navigationBarBackgroundColor": "#A3A9E4",
			"navigationBarTextStyle": "black"
		}
	},{
		"path": "pages/storeup/add-or-update",
		"style": {
			"navigationBarBackgroundColor": "#A3A9E4",
			"navigationBarTextStyle": "black"
		}
	},{
		"path": "pages/storeup/detail",
		"style": {
			"navigationBarBackgroundColor": "#A3A9E4",
			"navigationBarTextStyle": "black"
		}
	}
	,{
		"path": "pages/news/list",
		"style": {
			"navigationBarBackgroundColor": "#A3A9E4",
			"navigationBarTextStyle": "black"
		}
	},{
		"path": "pages/news/add-or-update",
		"style": {
			"navigationBarBackgroundColor": "#A3A9E4",
			"navigationBarTextStyle": "black"
		}
	},{
		"path": "pages/news/detail",
		"style": {
			"navigationBarBackgroundColor": "#A3A9E4",
			"navigationBarTextStyle": "black"
		}
	}
	,{
		"path": "pages/discussjingdianxinxi/list",
		"style": {
			"navigationBarBackgroundColor": "#A3A9E4",
			"navigationBarTextStyle": "black"
		}
	},{
		"path": "pages/discussjingdianxinxi/add-or-update",
		"style": {
			"navigationBarBackgroundColor": "#A3A9E4",
			"navigationBarTextStyle": "black"
		}
	},{
		"path": "pages/discussjingdianxinxi/detail",
		"style": {
			"navigationBarBackgroundColor": "#A3A9E4",
			"navigationBarTextStyle": "black"
		}
	}
    , {
		"path": "pages/forum-index/forum-index",
		"style": {
			"navigationBarBackgroundColor": "#A4A8E2",
			"navigationBarTextStyle": "black",
			"navigationBarTitleText": "首页"
		}
	}, {
		"path": "pages/forum-detail/forum-detail",
		"style": {
			"navigationBarBackgroundColor": "#A3A9E4",
			"navigationBarTextStyle": "black",
			"navigationBarTitleText": "论坛发帖详情"
		}
	}, {
		"path": "pages/forum-reply/forum-reply",
		"style": {
			"navigationBarBackgroundColor": "#A3A9E4",
			"navigationBarTextStyle": "black",
			"navigationBarTitleText": "回复评论"
		}
	}, {
		"path": "pages/forum-list/list",
		"style": {
			"navigationBarBackgroundColor": "#A3A9E4",
			"navigationBarTextStyle": "black",
			"navigationBarTitleText": "我的发布"
		}
	}, {
		"path": "pages/forum-my/forum-my",
		"style": {
			"navigationBarBackgroundColor": "#A3A9E4",
			"navigationBarTextStyle": "black",
			"navigationBarTitleText": "我的发布"
		}
	}, {
		"path": "pages/forum-add-or-update/forum-add-or-update",
		"style": {
			"navigationBarBackgroundColor": "#A3A9E4",
			"navigationBarTextStyle": "black",
			"navigationBarTitleText": "我的发布"
		}
	}
	, {
		"path": "pages/pay-confirm/pay-confirm",
		"style": {
			"navigationBarTitleText": "确认支付"
		}
	}
    ,{
        "path": "common/linkOthers/linkOthers",
        "style": {
			"navigationBarBackgroundColor": "#A4A8E2",
			"navigationBarTextStyle": "black"
        }
    }
	, {
		"path": "pages/index/index",
		"style": {
			"navigationBarBackgroundColor": "#A4A8E2",
			"navigationBarTextStyle": "black",
			"navigationBarTitleText": "首页"
		}
	}
	],
	"globalStyle": {
		"navigationBarTextStyle": "black",
		"navigationBarTitleText": "自驾游拼团小程序的设计与实现",
		"navigationBarBackgroundColor": "#F8F8F8",
		"backgroundColor": "#F8F8F8"
	},
	"tabBar": {
		"color": "#BBBBBB",
		"selectedColor": "#A3A9E4",
		"borderStyle": "white",
		"backgroundColor": "#FFFFFF",
		"list": [{
				"pagePath": "pages/index/index",
				"iconPath": "static/tabs/index.png",
				"selectedIconPath": "static/tabs/index1.png",
				"text": "首页"
			}
			

			,{
				"pagePath": "pages/jingdianxinxi/list",
				"iconPath": "/static/tabs/icon1.png",
				"selectedIconPath": "/static/tabs/icon1_act.png",
				"text": "景点信息"
			}
			,{
				"pagePath": "pages/pintuanlvyou/list",
				"iconPath": "/static/tabs/icon2.png",
				"selectedIconPath": "/static/tabs/icon2_act.png",
				"text": "拼团旅游"
			}




			,{
			 	"pagePath": "pages/forum-index/forum-index",
				"iconPath": "static/tabs/forum.png",
			 	"selectedIconPath": "static/tabs/forum_act.png",
				"text": "论坛"
			}


			,{
				"pagePath": "pages/center/center",
				"iconPath": "static/tabs/mine.png",
				"selectedIconPath": "static/tabs/mine1.png",
				"text": "我的"
			}
		]
	}
}
